{
	"parent": "quest_giver:root",
	"reputation": 15,
	"icon": "minecraft:iron_sword",
	"start": {
		"title": {
			"text": "それで？"
		},
		"description": {
			"text": "20個のエメラルドで「カウンターアタック」ってスキルを教えてあげるよ。どうする？"
		}
	},
	"complete": {
		"title": {
			"text": "ありがとう！"
		},
		"description": {
			"text": "楽しんでくれ！"
		}
	},
	"tasks": [{
		"item": {
			"item": "minecraft:emerald"
		},
      "id": "quest_giver:gift",
      "times": 20
	}],
	"rewards": [{
		"command": "give @p epicfight:skillbook{skill:\"wom:counter_attack\"}",
		"id": "quest_giver:command"
	}]
}